miniwdl_s3upload.py
miniwdl_s3upload-0.0.8.dist-info/METADATA
miniwdl_s3upload-0.0.8.dist-info/WHEEL
miniwdl_s3upload-0.0.8.dist-info/entry_points.txt
miniwdl_s3upload-0.0.8.dist-info/top_level.txt
miniwdl_s3upload-0.0.8.dist-info/RECORD
