Metadata-Version: 2.1
Name: miniwdl-s3upload
Version: 0.0.8
Summary: miniwdl plugin for progressive upload of task output files to Amazon S3
Home-page: https://github.com/chanzuckerberg/miniwdl-s3upload
Author: Mike Lin, Andrey Kislyuk
License: UNKNOWN
Project-URL: Documentation, https://github.com/chanzuckerberg/miniwdl-s3upload
Project-URL: Source Code, https://github.com/chanzuckerberg/miniwdl-s3upload
Project-URL: Issue Tracker, https://github.com/chanzuckerberg/miniwdl-s3upload/issues
Platform: UNKNOWN
Requires-Python: >=3.6
Requires-Dist: boto3
